babydb/__init__.py
babydb/cli.py
babydb/core.py
babydb/test.py
babydb/web.py
babydb-1.0.1.dist-info/licenses/LICENCE
tests/__init__.py
tests/test_simpledb.py
babydb-1.0.1.dist-info/METADATA
babydb-1.0.1.dist-info/WHEEL
babydb-1.0.1.dist-info/entry_points.txt
babydb-1.0.1.dist-info/top_level.txt
babydb-1.0.1.dist-info/RECORD
